RISCV_single/src/Controllers/interconnect_controller.v
// module interconnect_controller(

//     input clk,
//     input rst,

//     //=========================================
//     // CACHE CONTROLLER SIDE
//     //=========================================

//     input         cache_read_req,
//     input         cache_write_req,

//     input  [31:0] cache_address,
//     input  [31:0] cache_write_data,
//     input  [3:0]  cache_write_strb,

//     output reg [31:0] cache_read_data,
//     output reg        cache_read_done,
//     output reg        cache_write_done,
//     output reg        cache_busy,


//     //=========================================
//     // INTERCONNECT MASTER SIDE
//     //=========================================

//     output reg [31:0] master_read_addr,
//     output reg        master_read_addr_valid,
//     input             master_read_addr_ready,

//     input      [31:0] master_read_data,
//     input      [1:0]  master_read_resp,
//     input             master_read_data_valid,
//     output reg        master_read_data_ready,


//     output reg [31:0] master_write_addr,
//     output reg        master_write_addr_valid,
//     input             master_write_addr_ready,

//     output reg [31:0] master_write_data,
//     output reg [3:0]  master_write_strb,
//     output reg        master_write_data_valid,
//     input             master_write_data_ready,

//     input      [1:0]  master_write_resp,
//     input             master_write_resp_valid,
//     output reg        master_write_resp_ready

// );

// reg [2:0] state;
// reg [2:0] next_state;

// reg        req_is_read;
// reg        req_is_write;

// reg [31:0] req_address;
// reg [31:0] req_write_data;
// reg [3:0]  req_write_strb;

// parameter IDLE       = 3'b000;
// parameter READ_ADDR  = 3'b001;
// parameter READ_DATA  = 3'b010;
// parameter WRITE      = 3'b011;
// parameter WRITE_RESP = 3'b100;


// //======================================================
// // STATE REGISTER
// //======================================================

// // always @(posedge clk or posedge rst) begin

// //     if(rst)
// //         state <= IDLE;
// //     else
// //         state <= next_state;

// // end

// always @(posedge clk or posedge rst) begin
//     $display("STATE REG: t=%0t rst=%b state=%0d next=%0d",
//              $time, rst, state, next_state);

//     if (rst)
//         state <= IDLE;
//     else
//         state <= next_state;
// end

// //internal reg to make sure no inconsistencies,latch onto o/p
// always @(posedge clk or posedge rst) begin

//     if(rst) begin

//         req_is_read    <= 1'b0;
//         req_is_write   <= 1'b0;

//         req_address    <= 32'b0;
//         req_write_data <= 32'b0;
//         req_write_strb <= 4'b0;

//     end

//     else if(state == IDLE) begin

//         if(cache_read_req) begin

//             req_is_read    <= 1'b1;
//             req_is_write   <= 1'b0;

//             req_address    <= cache_address;

//         end

//         else if(cache_write_req) begin

//             req_is_read    <= 1'b0;
//             req_is_write   <= 1'b1;

//             req_address    <= cache_address;
//             req_write_data <= cache_write_data;
//             req_write_strb <= cache_write_strb;

//         end

//     end

// end

// //======================================================
// // NEXT STATE + OUTPUT LOGIC
// //======================================================




// // always @(*) begin

// //     //-------------------------------
// //     // Defaults
// //     //-------------------------------

// //     next_state = state;

// //     cache_busy       = (state != IDLE);

// //     cache_read_done  = 1'b0;
// //     cache_write_done = 1'b0;

// //     cache_read_data  = 32'b0;

// //     master_read_addr       = 32'b0;
// //     master_read_addr_valid = 1'b0;
// //     master_read_data_ready = 1'b0;

// //     master_write_addr       = 32'b0;
// //     master_write_addr_valid = 1'b0;
// //     master_write_data       = 32'b0;
// //     master_write_strb       = 4'b0;
// //     master_write_data_valid = 1'b0;
// //     master_write_resp_ready = 1'b0;

// //     //--------------------------------
// //     // FSM
// //     //--------------------------------

// //     case(state)

// //     //--------------------------------
// //     // IDLE
// //     //--------------------------------

// //     IDLE:
// //     begin

// //         if(cache_read_req)
// //             next_state = READ_ADDR;

// //         else if(cache_write_req)
// //             next_state = WRITE;

// //     end


// //     //--------------------------------
// //     // SEND READ ADDRESS
// //     //--------------------------------

// //     READ_ADDR:
// //     begin

       

// //         master_read_addr = req_address;
// //         master_read_addr_valid = 1'b1;

// //         if(master_read_addr_ready)
// //             next_state = READ_DATA;

// //     end



// //     //--------------------------------
// //     // WAIT FOR READ DATA
// //     //--------------------------------

// //     READ_DATA:
// //     begin

// //         master_read_data_ready = 1'b1;

// //         if(master_read_data_valid) begin

// //             if(master_read_resp == 2'b00) begin

// //                 cache_read_done = 1'b1;
// //                 cache_read_data = master_read_data;

// //             end

// //             next_state = IDLE;

// //         end

// //     end


// //     //--------------------------------
// //     // SEND WRITE
// //     //--------------------------------

// //     WRITE:
// //     begin

// //         master_write_addr = req_address;
// //         master_write_addr_valid = 1'b1;

// //         master_write_data = req_write_data;
// //         master_write_strb = req_write_strb;
// //         master_write_data_valid = 1'b1;

// //         if(master_write_addr_ready &&
// //            master_write_data_ready)

// //             next_state = WRITE_RESP;

// //     end


// //     //--------------------------------
// //     // WAIT FOR WRITE RESPONSE
// //     //--------------------------------

// //     WRITE_RESP:
// //     begin

// //         master_write_resp_ready = 1'b1;

// //         if(master_write_resp_valid) begin

// //             if(master_write_resp == 2'b00)
// //                 cache_write_done = 1'b1;

// //             next_state = IDLE;

// //         end

// //     end


// //     default:
// //     begin

// //         next_state = IDLE;

// //     end

// //     endcase

// // end

// always @(*) begin
//     next_state = state;

//     cache_busy = 0;
//     cache_read_done = 0;
//     cache_write_done = 0;
//     cache_read_data = 0;

//     master_read_addr = 0;
//     master_read_addr_valid = 0;
//     master_read_data_ready = 0;

//     master_write_addr = 0;
//     master_write_addr_valid = 0;
//     master_write_data = 0;
//     master_write_strb = 0;
//     master_write_data_valid = 0;
//     master_write_resp_ready = 0;
// end


// always @(posedge clk)
// begin
//     $display("IC: state=%0d next=%0d ARVALID=%b ARREADY=%b RVALID=%b RREADY=%b",
//         state,next_state,
//         master_read_addr_valid,
//         master_read_addr_ready,
//         master_read_data_valid,
//         master_read_data_ready);
// end

// endmodule

module interconnect_controller(
    input  wire        clk,
    input  wire        rst,

    //=========================================
    // CACHE CONTROLLER SIDE
    //=========================================
    input  wire        cache_read_req,
    input  wire        cache_write_req,
    input  wire [31:0] cache_address,
    input  wire [31:0] cache_write_data,
    input  wire [3:0]  cache_write_strb,

    output reg  [31:0] cache_read_data,
    output reg         cache_read_done,
    output reg         cache_write_done,
    output reg         cache_busy,

    //=========================================
    // INTERCONNECT MASTER SIDE
    //=========================================
    output reg  [31:0] master_read_addr,
    output reg         master_read_addr_valid,
    input  wire        master_read_addr_ready,

    input  wire [31:0] master_read_data,
    input  wire [1:0]  master_read_resp,
    input  wire        master_read_data_valid,
    output reg         master_read_data_ready,

    output reg  [31:0] master_write_addr,
    output reg         master_write_addr_valid,
    input  wire        master_write_addr_ready,

    output reg  [31:0] master_write_data,
    output reg  [3:0]  master_write_strb,
    output reg         master_write_data_valid,
    input  wire        master_write_data_ready,

    input  wire [1:0]  master_write_resp,
    input  wire        master_write_resp_valid,
    output reg         master_write_resp_ready
);

    //======================================================
    // STATE DEFINITIONS
    //======================================================
    parameter IDLE       = 3'b000;
    parameter READ_ADDR  = 3'b001;
    parameter READ_DATA  = 3'b010;
    parameter WRITE      = 3'b011;
    parameter WRITE_RESP = 3'b100;

    reg [2:0] state;
    reg [2:0] next_state;

    // Latched request parameters
    reg [31:0] req_address;
    reg [31:0] req_write_data;
    reg [3:0]  req_write_strb;

    //======================================================
    // STATE REGISTER
    //======================================================
    always @(posedge clk or posedge rst) begin
        if (rst) begin
            state <= IDLE;
        end
        else begin
            state <= next_state;
    end

end

    //======================================================
    // INPUT LATCHING
    //======================================================
    always @(posedge clk or posedge rst) begin
        if(rst) begin
            req_address    <= 32'b0;
            req_write_data <= 32'b0;
            req_write_strb <= 4'b0;
        end
        else if(state == IDLE) begin
            if(cache_read_req) begin
                req_address    <= cache_address;
            end
            else if(cache_write_req) begin
                req_address    <= cache_address;
                req_write_data <= cache_write_data;
                req_write_strb <= cache_write_strb;
            end
        end
    end

    //======================================================
    // NEXT STATE + OUTPUT LOGIC (FSM)
    //======================================================
    always @(*) begin

        //-------------------------------
        // Defaults to prevent latches
        //-------------------------------
        next_state              = state;
        
        cache_busy              = (state != IDLE);
        cache_read_done         = 1'b0;
        cache_write_done        = 1'b0;
        cache_read_data         = 32'b0;

        master_read_addr        = 32'b0;
        master_read_addr_valid  = 1'b0;
        master_read_data_ready  = 1'b0;

        master_write_addr       = 32'b0;
        master_write_addr_valid = 1'b0;
        master_write_data       = 32'b0;
        master_write_strb       = 4'b0;
        master_write_data_valid = 1'b0;
        master_write_resp_ready = 1'b0;

        //--------------------------------
        // FSM Logic
        //--------------------------------
        case(state)
            IDLE: begin
                if(cache_read_req)
                    next_state = READ_ADDR;
                else if(cache_write_req)
                    next_state = WRITE;
            end

            READ_ADDR: begin
                master_read_addr = req_address;
                master_read_addr_valid = 1'b1;

                if(master_read_addr_ready)
                    next_state = READ_DATA;
            end

            READ_DATA: begin
                master_read_data_ready = 1'b1;

                if(master_read_data_valid) begin
                    if(master_read_resp == 2'b00) begin
                        cache_read_done = 1'b1;
                        cache_read_data = master_read_data;
                    end
                    next_state = IDLE;
                end
            end

            WRITE: begin
                master_write_addr = req_address;
                master_write_addr_valid = 1'b1;

                master_write_data = req_write_data;
                master_write_strb = req_write_strb;
                master_write_data_valid = 1'b1;

                if(master_write_addr_ready && master_write_data_ready)
                    next_state = WRITE_RESP;
            end

            WRITE_RESP: begin
                master_write_resp_ready = 1'b1;

                if(master_write_resp_valid) begin
                    if(master_write_resp == 2'b00)
                        cache_write_done = 1'b1;
                        
                    next_state = IDLE;
                end
            end

            default: begin
                next_state = IDLE;
            end
        endcase
    end

    //======================================================
    // DEBUG MONITORING
    //======================================================



endmodule

RISCV_single/src/testbench/tb_ic_axi_memctrl.v
`timescale 1ns/1ps

module tb_ic_axi_memctrl;

    reg clk;
    reg rst;

    //==================================================
    // Hand-driven "cache" side
    //==================================================
    reg         cache_read_req;
    reg         cache_write_req;
    reg  [31:0] cache_address;
    reg  [31:0] cache_write_data;
    reg  [3:0]  cache_write_strb;

    wire [31:0] cache_read_data;
    wire        cache_read_done;
    wire        cache_write_done;
    wire        cache_busy;

    //==================================================
    // Interconnect Controller <-> AXI
    //==================================================
    wire [31:0] ic_master_read_addr;
    wire        ic_master_read_addr_valid;
    wire        ic_master_read_addr_ready;

    wire [31:0] ic_master_read_data;
    wire [1:0]  ic_master_read_resp;
    wire        ic_master_read_data_valid;
    wire        ic_master_read_data_ready;

    wire [31:0] ic_master_write_addr;
    wire        ic_master_write_addr_valid;
    wire        ic_master_write_addr_ready;

    wire [31:0] ic_master_write_data;
    wire [3:0]  ic_master_write_strb;
    wire        ic_master_write_data_valid;
    wire        ic_master_write_data_ready;

    wire [1:0]  ic_master_write_resp;
    wire        ic_master_write_resp_valid;
    wire        ic_master_write_resp_ready;

    //==================================================
    // AXI <-> Memory Controller (Signals)
    //==================================================
    wire [31:0] mem_read_addr;
    wire        mem_read_addr_valid;
    wire        mem_read_addr_ready;

    wire [31:0] mem_read_data;
    wire [1:0]  mem_read_resp;
    wire        mem_read_data_valid;
    wire        mem_read_data_ready;

    wire [31:0] mem_write_addr;
    wire        mem_write_addr_valid;
    wire        mem_write_addr_ready;

    wire [31:0] mem_write_data;
    wire [3:0]  mem_write_strb;
    wire        mem_write_data_valid;
    wire        mem_write_data_ready;

    wire [1:0]  mem_write_resp;
    wire        mem_write_resp_valid;
    wire        mem_write_resp_ready;

    wire        memory_busy;

    //==================================================
    // DUT: Interconnect Controller
    //==================================================
    interconnect_controller ic_inst(
        .clk(clk),
        .rst(rst),

        .cache_read_req(cache_read_req),
        .cache_write_req(cache_write_req),
        .cache_address(cache_address),
        .cache_write_data(cache_write_data),
        .cache_write_strb(cache_write_strb),

        .cache_read_data(cache_read_data),
        .cache_read_done(cache_read_done),
        .cache_write_done(cache_write_done),
        .cache_busy(cache_busy),

        .master_read_addr(ic_master_read_addr),
        .master_read_addr_valid(ic_master_read_addr_valid),
        .master_read_addr_ready(ic_master_read_addr_ready),

        .master_read_data(ic_master_read_data),
        .master_read_resp(ic_master_read_resp),
        .master_read_data_valid(ic_master_read_data_valid),
        .master_read_data_ready(ic_master_read_data_ready),

        .master_write_addr(ic_master_write_addr),
        .master_write_addr_valid(ic_master_write_addr_valid),
        .master_write_addr_ready(ic_master_write_addr_ready),

        .master_write_data(ic_master_write_data),
        .master_write_strb(ic_master_write_strb),
        .master_write_data_valid(ic_master_write_data_valid),
        .master_write_data_ready(ic_master_write_data_ready),

        .master_write_resp(ic_master_write_resp),
        .master_write_resp_valid(ic_master_write_resp_valid),
        .master_write_resp_ready(ic_master_write_resp_ready)
    );

    // Pass-through assignments (acting as interconnect wiring)
    assign mem_read_addr              = ic_master_read_addr;
    assign mem_read_addr_valid        = ic_master_read_addr_valid;
    assign ic_master_read_addr_ready  = mem_read_addr_ready;

    assign ic_master_read_data        = mem_read_data;
    assign ic_master_read_resp        = mem_read_resp;
    assign ic_master_read_data_valid  = mem_read_data_valid;
    assign mem_read_data_ready        = ic_master_read_data_ready;

    assign mem_write_addr             = ic_master_write_addr;
    assign mem_write_addr_valid       = ic_master_write_addr_valid;
    assign ic_master_write_addr_ready = mem_write_addr_ready;

    assign mem_write_data             = ic_master_write_data;
    assign mem_write_strb             = ic_master_write_strb;
    assign mem_write_data_valid       = ic_master_write_data_valid;
    assign ic_master_write_data_ready = mem_write_data_ready;

    assign ic_master_write_resp       = mem_write_resp;
    assign ic_master_write_resp_valid = mem_write_resp_valid;
    assign mem_write_resp_ready       = ic_master_write_resp_ready;

    //==================================================
    // FAKE MEMORY SLAVE RESPONSES
    //==================================================
    reg mem_read_data_valid_r;
    reg mem_write_resp_valid_r;

    // READ CHANNEL
    assign mem_read_addr_ready = 1'b1;
    assign mem_read_data       = 32'h12345678;
    assign mem_read_resp       = 2'b00;
    assign mem_read_data_valid = mem_read_data_valid_r;

    // WRITE CHANNEL
    assign mem_write_addr_ready = 1'b1;
    assign mem_write_data_ready = 1'b1;
    assign mem_write_resp       = 2'b00;
    assign mem_write_resp_valid = mem_write_resp_valid_r;

    //==================================================
    // Clock
    //==================================================
    always #5 clk = ~clk;

    //==================================================
    // Waveform dump
    //==================================================
    initial begin
        $dumpfile("ic_axi_mc.vcd");
        $dumpvars(0, tb_ic_axi_memctrl);
    end

    //==================================================
    // Monitor
    //==================================================
    always @(posedge clk) begin
        $display("t=%0t | IC=%0d | creq=%b cwreq=%b cdone=%b cwdone=%b | ARV=%b ARR=%b RV=%b RR=%b | AWV=%b AWR=%b WV=%b WR=%b BV=%b BR=%b",
            $time, ic_inst.state, 
            cache_read_req, cache_write_req, cache_read_done, cache_write_done,
            ic_master_read_addr_valid, ic_master_read_addr_ready,
            ic_master_read_data_valid, ic_master_read_data_ready,
            ic_master_write_addr_valid, ic_master_write_addr_ready,
            ic_master_write_data_valid, ic_master_write_data_ready,
            ic_master_write_resp_valid, ic_master_write_resp_ready);
    end

    //==================================================
    // Timeout
    //==================================================
    initial begin
        #1000;
        $display("*** TIMEOUT ***");
        $finish;
    end

    //==================================================
    // Test Sequence
    //==================================================
    initial begin
        clk = 0;
        rst = 1;

        cache_read_req   = 0;
        cache_write_req  = 0;
        cache_address    = 0;
        cache_write_data = 0;
        cache_write_strb = 0;

        mem_read_data_valid_r  = 0;
        mem_write_resp_valid_r = 0;

        #20;
        rst = 0;
        @(negedge clk);

        //--------------------------------------------------
        // READ TEST
        //--------------------------------------------------
        cache_read_req = 1;
        cache_address  = 32'h100;

        // Wait for IC to output ARVALID to the bus
        wait(ic_master_read_addr_valid);
        @(posedge clk); 

        cache_read_req = 0; // <-- Moved up: Emulating true cache pulse behavior

        // Fake slave answers with valid data
        mem_read_data_valid_r = 1;

        // Wait for the IC to tell the cache it's done
        wait(cache_read_done);
        @(posedge clk); 

        // Deassert signals
        mem_read_data_valid_r = 0;

        $display("READ DONE @ %0t, data=%h", $time, cache_read_data);

        // Small delay between tests
        repeat(5) @(posedge clk);

        //--------------------------------------------------
        // WRITE TEST
        //--------------------------------------------------
        cache_write_req  = 1;
        cache_address    = 32'h200;
        cache_write_data = 32'hDEADBEEF;
        cache_write_strb = 4'b1111;

        // Wait for IC to output AWVALID and WVALID to the bus
        wait(ic_master_write_addr_valid && ic_master_write_data_valid);
        @(posedge clk); 

        cache_write_req = 0; // <-- Moved up: Emulating true cache pulse behavior

        // Fake slave answers with valid write response
        mem_write_resp_valid_r = 1;

        // Wait for the IC to tell the cache it's done
        wait(cache_write_done);
        @(posedge clk); 

        // Deassert signals
        mem_write_resp_valid_r = 0;

        $display("WRITE DONE @ %0t", $time);

        #20;
        $display("SIMULATION FINISHED CLEANLY");
        $finish;
    end

endmodule

RISCV_single/src/ic_axi_mc.vcd
$date
	Tue Jul 07 15:47:18 2026
$end
$version
	Icarus Verilog
$end
$timescale
	1ps
$end
$scope module tb_ic_axi_memctrl $end
$var wire 1 ! ic_master_read_addr_ready $end
$var wire 32 " ic_master_read_data [31:0] $end
$var wire 1 # ic_master_read_data_valid $end
$var wire 2 $ ic_master_read_resp [1:0] $end
$var wire 1 % ic_master_write_addr_ready $end
$var wire 1 & ic_master_write_data_ready $end
$var wire 2 ' ic_master_write_resp [1:0] $end
$var wire 1 ( ic_master_write_resp_valid $end
$var wire 32 ) mem_read_addr [31:0] $end
$var wire 1 * mem_read_addr_ready $end
$var wire 1 + mem_read_addr_valid $end
$var wire 32 , mem_read_data [31:0] $end
$var wire 1 - mem_read_data_ready $end
$var wire 2 . mem_read_resp [1:0] $end
$var wire 32 / mem_write_addr [31:0] $end
$var wire 1 0 mem_write_addr_ready $end
$var wire 1 1 mem_write_addr_valid $end
$var wire 32 2 mem_write_data [31:0] $end
$var wire 1 3 mem_write_data_ready $end
$var wire 1 4 mem_write_data_valid $end
$var wire 2 5 mem_write_resp [1:0] $end
$var wire 1 6 mem_write_resp_ready $end
$var wire 4 7 mem_write_strb [3:0] $end
$var wire 1 8 mem_write_resp_valid $end
$var wire 1 9 mem_read_data_valid $end
$var wire 4 : ic_master_write_strb [3:0] $end
$var wire 1 ; ic_master_write_resp_ready $end
$var wire 1 < ic_master_write_data_valid $end
$var wire 32 = ic_master_write_data [31:0] $end
$var wire 1 > ic_master_write_addr_valid $end
$var wire 32 ? ic_master_write_addr [31:0] $end
$var wire 1 @ ic_master_read_data_ready $end
$var wire 1 A ic_master_read_addr_valid $end
$var wire 32 B ic_master_read_addr [31:0] $end
$var wire 1 C cache_write_done $end
$var wire 1 D cache_read_done $end
$var wire 32 E cache_read_data [31:0] $end
$var wire 1 F cache_busy $end
$var reg 32 G cache_address [31:0] $end
$var reg 1 H cache_read_req $end
$var reg 32 I cache_write_data [31:0] $end
$var reg 1 J cache_write_req $end
$var reg 4 K cache_write_strb [3:0] $end
$var reg 1 L clk $end
$var reg 1 9 mem_read_data_valid_r $end
$var reg 1 8 mem_write_resp_valid_r $end
$var reg 1 M rst $end
$scope module ic_inst $end
$var wire 32 N cache_address [31:0] $end
$var wire 1 H cache_read_req $end
$var wire 32 O cache_write_data [31:0] $end
$var wire 1 J cache_write_req $end
$var wire 4 P cache_write_strb [3:0] $end
$var wire 1 L clk $end
$var wire 1 ! master_read_addr_ready $end
$var wire 32 Q master_read_data [31:0] $end
$var wire 1 # master_read_data_valid $end
$var wire 2 R master_read_resp [1:0] $end
$var wire 1 % master_write_addr_ready $end
$var wire 1 & master_write_data_ready $end
$var wire 2 S master_write_resp [1:0] $end
$var wire 1 ( master_write_resp_valid $end
$var wire 1 M rst $end
$var parameter 3 T IDLE $end
$var parameter 3 U READ_ADDR $end
$var parameter 3 V READ_DATA $end
$var parameter 3 W WRITE $end
$var parameter 3 X WRITE_RESP $end
$var reg 1 F cache_busy $end
$var reg 32 Y cache_read_data [31:0] $end
$var reg 1 D cache_read_done $end
$var reg 1 C cache_write_done $end
$var reg 32 Z master_read_addr [31:0] $end
$var reg 1 A master_read_addr_valid $end
$var reg 1 @ master_read_data_ready $end
$var reg 32 [ master_write_addr [31:0] $end
$var reg 1 > master_write_addr_valid $end
$var reg 32 \ master_write_data [31:0] $end
$var reg 1 < master_write_data_valid $end
$var reg 1 ; master_write_resp_ready $end
$var reg 4 ] master_write_strb [3:0] $end
$var reg 3 ^ next_state [2:0] $end
$var reg 32 _ req_address [31:0] $end
$var reg 32 ` req_write_data [31:0] $end
$var reg 4 a req_write_strb [3:0] $end
$var reg 3 b state [2:0] $end
$upscope $end
$upscope $end
$enddefinitions $end
$comment Show the parameter values. $end
$dumpall
b100 X
b11 W
b10 V
b1 U
b0 T
$end
#0
$dumpvars
b0 b
b0 a
b0 `
b0 _
b0 ^
b0 ]
b0 \
b0 [
b0 Z
b0 Y
b0 S
b0 R
b10010001101000101011001111000 Q
b0 P
b0 O
b0 N
1M
0L
b0 K
0J
b0 I
0H
b0 G
0F
b0 E
0D
0C
b0 B
0A
0@
b0 ?
0>
b0 =
0<
0;
b0 :
09
08
b0 7
06
b0 5
04
13
b0 2
01
10
b0 /
b0 .
0-
b10010001101000101011001111000 ,
0+
1*
b0 )
0(
b0 '
1&
1%
b0 $
0#
b10010001101000101011001111000 "
1!
$end
#5000
1L
#10000
0L
#15000
1L
#20000
b1 ^
b100000000 G
b100000000 N
1H
0L
0M
#25000
b10 ^
1+
1A
b100000000 )
b100000000 B
b100000000 Z
1F
b100000000 _
b1 b
1L
#30000
0L
#35000
b10010001101000101011001111000 E
b10010001101000101011001111000 Y
1D
1-
1@
b10 b
0+
0A
b0 )
b0 B
b0 Z
b0 ^
1#
19
0H
1L
#40000
0L
#45000
0F
b0 b
0-
0@
b0 E
b0 Y
0D
b0 ^
0#
09
1L
#50000
0L
#55000
1L
#60000
0L
#65000
1L
#70000
0L
#75000
1L
#80000
0L
#85000
1L
#90000
0L
#95000
b11 ^
b1111 K
b1111 P
b11011110101011011011111011101111 I
b11011110101011011011111011101111 O
b1000000000 G
b1000000000 N
1J
1L
#100000
0L
#105000
b100 ^
14
1<
b1111 7
b1111 :
b1111 ]
b11011110101011011011111011101111 2
b11011110101011011011111011101111 =
b11011110101011011011111011101111 \
11
1>
b1000000000 /
b1000000000 ?
b1000000000 [
1F
b1111 a
b11011110101011011011111011101111 `
b1000000000 _
b11 b
1L
#110000
0L
#115000
1C
16
1;
b100 b
04
0<
b0 7
b0 :
b0 ]
b0 2
b0 =
b0 \
01
0>
b0 /
b0 ?
b0 [
b0 ^
1(
18
0J
1L
#120000
0L
#125000
0F
b0 b
06
0;
0C
b0 ^
0(
08
1L
