RISCV_single/src/Controllers/interconnect_controller.v
// module interconnect_controller(

//     input clk,
//     input rst,

//     //=========================================
//     // CACHE CONTROLLER SIDE
//     //=========================================

//     input         cache_read_req,
//     input         cache_write_req,

//     input  [31:0] cache_address,
//     input  [31:0] cache_write_data,
//     input  [3:0]  cache_write_strb,

//     output reg [31:0] cache_read_data,
//     output reg        cache_read_done,
//     output reg        cache_write_done,
//     output reg        cache_busy,


//     //=========================================
//     // INTERCONNECT MASTER SIDE
//     //=========================================

//     output reg [31:0] master_read_addr,
//     output reg        master_read_addr_valid,
//     input             master_read_addr_ready,

//     input      [31:0] master_read_data,
//     input      [1:0]  master_read_resp,
//     input             master_read_data_valid,
//     output reg        master_read_data_ready,


//     output reg [31:0] master_write_addr,
//     output reg        master_write_addr_valid,
//     input             master_write_addr_ready,

//     output reg [31:0] master_write_data,
//     output reg [3:0]  master_write_strb,
//     output reg        master_write_data_valid,
//     input             master_write_data_ready,

//     input      [1:0]  master_write_resp,
//     input             master_write_resp_valid,
//     output reg        master_write_resp_ready

// );

// reg [2:0] state;
// reg [2:0] next_state;

// reg        req_is_read;
// reg        req_is_write;

// reg [31:0] req_address;
// reg [31:0] req_write_data;
// reg [3:0]  req_write_strb;

// parameter IDLE       = 3'b000;
// parameter READ_ADDR  = 3'b001;
// parameter READ_DATA  = 3'b010;
// parameter WRITE      = 3'b011;
// parameter WRITE_RESP = 3'b100;


// //======================================================
// // STATE REGISTER
// //======================================================

// // always @(posedge clk or posedge rst) begin

// //     if(rst)
// //         state <= IDLE;
// //     else
// //         state <= next_state;

// // end

// always @(posedge clk or posedge rst) begin
//     $display("STATE REG: t=%0t rst=%b state=%0d next=%0d",
//              $time, rst, state, next_state);

//     if (rst)
//         state <= IDLE;
//     else
//         state <= next_state;
// end

// //internal reg to make sure no inconsistencies,latch onto o/p
// always @(posedge clk or posedge rst) begin

//     if(rst) begin

//         req_is_read    <= 1'b0;
//         req_is_write   <= 1'b0;

//         req_address    <= 32'b0;
//         req_write_data <= 32'b0;
//         req_write_strb <= 4'b0;

//     end

//     else if(state == IDLE) begin

//         if(cache_read_req) begin

//             req_is_read    <= 1'b1;
//             req_is_write   <= 1'b0;

//             req_address    <= cache_address;

//         end

//         else if(cache_write_req) begin

//             req_is_read    <= 1'b0;
//             req_is_write   <= 1'b1;

//             req_address    <= cache_address;
//             req_write_data <= cache_write_data;
//             req_write_strb <= cache_write_strb;

//         end

//     end

// end

// //======================================================
// // NEXT STATE + OUTPUT LOGIC
// //======================================================




// // always @(*) begin

// //     //-------------------------------
// //     // Defaults
// //     //-------------------------------

// //     next_state = state;

// //     cache_busy       = (state != IDLE);

// //     cache_read_done  = 1'b0;
// //     cache_write_done = 1'b0;

// //     cache_read_data  = 32'b0;

// //     master_read_addr       = 32'b0;
// //     master_read_addr_valid = 1'b0;
// //     master_read_data_ready = 1'b0;

// //     master_write_addr       = 32'b0;
// //     master_write_addr_valid = 1'b0;
// //     master_write_data       = 32'b0;
// //     master_write_strb       = 4'b0;
// //     master_write_data_valid = 1'b0;
// //     master_write_resp_ready = 1'b0;

// //     //--------------------------------
// //     // FSM
// //     //--------------------------------

// //     case(state)

// //     //--------------------------------
// //     // IDLE
// //     //--------------------------------

// //     IDLE:
// //     begin

// //         if(cache_read_req)
// //             next_state = READ_ADDR;

// //         else if(cache_write_req)
// //             next_state = WRITE;

// //     end


// //     //--------------------------------
// //     // SEND READ ADDRESS
// //     //--------------------------------

// //     READ_ADDR:
// //     begin

       

// //         master_read_addr = req_address;
// //         master_read_addr_valid = 1'b1;

// //         if(master_read_addr_ready)
// //             next_state = READ_DATA;

// //     end



// //     //--------------------------------
// //     // WAIT FOR READ DATA
// //     //--------------------------------

// //     READ_DATA:
// //     begin

// //         master_read_data_ready = 1'b1;

// //         if(master_read_data_valid) begin

// //             if(master_read_resp == 2'b00) begin

// //                 cache_read_done = 1'b1;
// //                 cache_read_data = master_read_data;

// //             end

// //             next_state = IDLE;

// //         end

// //     end


// //     //--------------------------------
// //     // SEND WRITE
// //     //--------------------------------

// //     WRITE:
// //     begin

// //         master_write_addr = req_address;
// //         master_write_addr_valid = 1'b1;

// //         master_write_data = req_write_data;
// //         master_write_strb = req_write_strb;
// //         master_write_data_valid = 1'b1;

// //         if(master_write_addr_ready &&
// //            master_write_data_ready)

// //             next_state = WRITE_RESP;

// //     end


// //     //--------------------------------
// //     // WAIT FOR WRITE RESPONSE
// //     //--------------------------------

// //     WRITE_RESP:
// //     begin

// //         master_write_resp_ready = 1'b1;

// //         if(master_write_resp_valid) begin

// //             if(master_write_resp == 2'b00)
// //                 cache_write_done = 1'b1;

// //             next_state = IDLE;

// //         end

// //     end


// //     default:
// //     begin

// //         next_state = IDLE;

// //     end

// //     endcase

// // end

// always @(*) begin
//     next_state = state;

//     cache_busy = 0;
//     cache_read_done = 0;
//     cache_write_done = 0;
//     cache_read_data = 0;

//     master_read_addr = 0;
//     master_read_addr_valid = 0;
//     master_read_data_ready = 0;

//     master_write_addr = 0;
//     master_write_addr_valid = 0;
//     master_write_data = 0;
//     master_write_strb = 0;
//     master_write_data_valid = 0;
//     master_write_resp_ready = 0;
// end


// always @(posedge clk)
// begin
//     $display("IC: state=%0d next=%0d ARVALID=%b ARREADY=%b RVALID=%b RREADY=%b",
//         state,next_state,
//         master_read_addr_valid,
//         master_read_addr_ready,
//         master_read_data_valid,
//         master_read_data_ready);
// end

// endmodule

module interconnect_controller(
    input  wire        clk,
    input  wire        rst,

    //=========================================
    // CACHE CONTROLLER SIDE
    //=========================================
    input  wire        cache_read_req,
    input  wire        cache_write_req,
    input  wire [31:0] cache_address,
    input  wire [31:0] cache_write_data,
    input  wire [3:0]  cache_write_strb,

    output reg  [31:0] cache_read_data,
    output reg         cache_read_done,
    output reg         cache_write_done,
    output reg         cache_busy,

    //=========================================
    // INTERCONNECT MASTER SIDE
    //=========================================
    output reg  [31:0] master_read_addr,
    output reg         master_read_addr_valid,
    input  wire        master_read_addr_ready,

    input  wire [31:0] master_read_data,
    input  wire [1:0]  master_read_resp,
    input  wire        master_read_data_valid,
    output reg         master_read_data_ready,

    output reg  [31:0] master_write_addr,
    output reg         master_write_addr_valid,
    input  wire        master_write_addr_ready,

    output reg  [31:0] master_write_data,
    output reg  [3:0]  master_write_strb,
    output reg         master_write_data_valid,
    input  wire        master_write_data_ready,

    input  wire [1:0]  master_write_resp,
    input  wire        master_write_resp_valid,
    output reg         master_write_resp_ready
);

    //======================================================
    // STATE DEFINITIONS
    //======================================================
    parameter IDLE       = 3'b000;
    parameter READ_ADDR  = 3'b001;
    parameter READ_DATA  = 3'b010;
    parameter WRITE      = 3'b011;
    parameter WRITE_RESP = 3'b100;

    reg [2:0] state;
    reg [2:0] next_state;

    // Latched request parameters
    reg [31:0] req_address;
    reg [31:0] req_write_data;
    reg [3:0]  req_write_strb;

    //======================================================
    // STATE REGISTER
    //======================================================
    always @(posedge clk or posedge rst) begin
        if (rst) begin
            state <= IDLE;
        end
        else begin
            state <= next_state;
    end

end

    //======================================================
    // INPUT LATCHING
    //======================================================
    always @(posedge clk or posedge rst) begin
        if(rst) begin
            req_address    <= 32'b0;
            req_write_data <= 32'b0;
            req_write_strb <= 4'b0;
        end
        else if(state == IDLE) begin
            if(cache_read_req) begin
                req_address    <= cache_address;
            end
            else if(cache_write_req) begin
                req_address    <= cache_address;
                req_write_data <= cache_write_data;
                req_write_strb <= cache_write_strb;
            end
        end
    end

    //======================================================
    // NEXT STATE + OUTPUT LOGIC (FSM)
    //======================================================
    always @(*) begin

        //-------------------------------
        // Defaults to prevent latches
        //-------------------------------
        next_state              = state;
        
        cache_busy              = (state != IDLE);
        cache_read_done         = 1'b0;
        cache_write_done        = 1'b0;
        cache_read_data         = 32'b0;

        master_read_addr        = 32'b0;
        master_read_addr_valid  = 1'b0;
        master_read_data_ready  = 1'b0;

        master_write_addr       = 32'b0;
        master_write_addr_valid = 1'b0;
        master_write_data       = 32'b0;
        master_write_strb       = 4'b0;
        master_write_data_valid = 1'b0;
        master_write_resp_ready = 1'b0;

        //--------------------------------
        // FSM Logic
        //--------------------------------
        case(state)
            IDLE: begin
                if(cache_read_req)
                    next_state = READ_ADDR;
                else if(cache_write_req)
                    next_state = WRITE;
            end

            READ_ADDR: begin
                master_read_addr = req_address;
                master_read_addr_valid = 1'b1;

                if(master_read_addr_ready)
                    next_state = READ_DATA;
            end

            READ_DATA: begin
                master_read_data_ready = 1'b1;

                if(master_read_data_valid) begin
                    if(master_read_resp == 2'b00) begin
                        cache_read_done = 1'b1;
                        cache_read_data = master_read_data;
                    end
                    next_state = IDLE;
                end
            end

            WRITE: begin
                master_write_addr = req_address;
                master_write_addr_valid = 1'b1;

                master_write_data = req_write_data;
                master_write_strb = req_write_strb;
                master_write_data_valid = 1'b1;

                if(master_write_addr_ready && master_write_data_ready)
                    next_state = WRITE_RESP;
            end

            WRITE_RESP: begin
                master_write_resp_ready = 1'b1;

                if(master_write_resp_valid) begin
                    if(master_write_resp == 2'b00)
                        cache_write_done = 1'b1;
                        
                    next_state = IDLE;
                end
            end

            default: begin
                next_state = IDLE;
            end
        endcase
    end

    //======================================================
    // DEBUG MONITORING
    //======================================================



endmodule

RISCV_single/src/testbench/tb_interconnect_controller.v
`timescale 1ns / 1ps

module tb_interconnect_controller;

reg clk;
reg rst;

//==================================================
// CACHE SIDE
//==================================================

reg         cache_read_req;
reg         cache_write_req;

reg [31:0]  cache_address;
reg [31:0]  cache_write_data;
reg [3:0]   cache_write_strb;

wire [31:0] cache_read_data;
wire        cache_read_done;
wire        cache_write_done;
wire        cache_busy;


//==================================================
// INTERCONNECT SIDE
//==================================================

wire [31:0] master_read_addr;
wire        master_read_addr_valid;
reg         master_read_addr_ready;

reg [31:0]  master_read_data;
reg [1:0]   master_read_resp;
reg         master_read_data_valid;
wire        master_read_data_ready;


wire [31:0] master_write_addr;
wire        master_write_addr_valid;
reg         master_write_addr_ready;

wire [31:0] master_write_data;
wire [3:0]  master_write_strb;
wire        master_write_data_valid;
reg         master_write_data_ready;

reg  [1:0]  master_write_resp;
reg         master_write_resp_valid;
wire        master_write_resp_ready;


//==================================================
// DUT
//==================================================

interconnect_controller dut(

    .clk(clk),
    .rst(rst),

    .cache_read_req(cache_read_req),
    .cache_write_req(cache_write_req),
    .cache_address(cache_address),
    .cache_write_data(cache_write_data),
    .cache_write_strb(cache_write_strb),

    .cache_read_data(cache_read_data),
    .cache_read_done(cache_read_done),
    .cache_write_done(cache_write_done),
    .cache_busy(cache_busy),

    .master_read_addr(master_read_addr),
    .master_read_addr_valid(master_read_addr_valid),
    .master_read_addr_ready(master_read_addr_ready),

    .master_read_data(master_read_data),
    .master_read_resp(master_read_resp),
    .master_read_data_valid(master_read_data_valid),
    .master_read_data_ready(master_read_data_ready),

    .master_write_addr(master_write_addr),
    .master_write_addr_valid(master_write_addr_valid),
    .master_write_addr_ready(master_write_addr_ready),

    .master_write_data(master_write_data),
    .master_write_strb(master_write_strb),
    .master_write_data_valid(master_write_data_valid),
    .master_write_data_ready(master_write_data_ready),

    .master_write_resp(master_write_resp),
    .master_write_resp_valid(master_write_resp_valid),
    .master_write_resp_ready(master_write_resp_ready)

);


//==================================================
// CLOCK
//==================================================

always #5 clk = ~clk;


//==================================================
// TEST
//==================================================

initial begin

    clk = 0;
    rst = 1;

    cache_read_req = 0;
    cache_write_req = 0;

    cache_address = 0;
    cache_write_data = 0;
    cache_write_strb = 0;

    master_read_addr_ready = 0;
    master_read_data = 0;
    master_read_resp = 2'b00;
    master_read_data_valid = 0;

    master_write_addr_ready = 0;
    master_write_data_ready = 0;
    master_write_resp = 2'b00;
    master_write_resp_valid = 0;

    //-------------------
    // RESET
    //-------------------

    #20;
    rst = 0;

    //-------------------
    // READ TEST
    //-------------------

    $display("==================================");
    $display("READ TEST");
    $display("==================================");

    cache_address = 32'h00000100;
    cache_read_req = 1;

    #10;

    cache_read_req = 0;

    // Wait a cycle
    #10;

    // Interconnect accepts address
    master_read_addr_ready = 1;

    #10;

    master_read_addr_ready = 0;

    // Wait 2 cycles (memory delay)
    #20;

    // Return read data
    master_read_data = 32'h12345678;
    master_read_resp = 2'b00;
    master_read_data_valid = 1;

    #10;

    master_read_data_valid = 0;

    #20;

    //-------------------
    // WRITE TEST
    //-------------------

    $display("==================================");
    $display("WRITE TEST");
    $display("==================================");

    cache_address = 32'h00000200;
    cache_write_data = 32'hDEADBEEF;
    cache_write_strb = 4'b1111;

    cache_write_req = 1;

    #10;

    cache_write_req = 0;

    // Interconnect accepts address/data
    #10;

    master_write_addr_ready = 1;
    master_write_data_ready = 1;

    #10;

    master_write_addr_ready = 0;
    master_write_data_ready = 0;

    // Memory takes time
    #20;

    master_write_resp = 2'b00;
    master_write_resp_valid = 1;

    #10;

    master_write_resp_valid = 0;

    #30;

    $display("Simulation Finished");

    $finish;

end


//==================================================
// MONITOR
//==================================================

initial begin

$monitor(
"Time=%0t | State=%d | Busy=%b | ReadReq=%b | WriteReq=%b | ReadDone=%b | WriteDone=%b | RAddr=%h | WAddr=%h | WData=%h",
$time,
dut.state,
cache_busy,
cache_read_req,
cache_write_req,
cache_read_done,
cache_write_done,
master_read_addr,
master_write_addr,
master_write_data
);

end


//==================================================
// WAVES
//==================================================

initial begin

    $dumpfile("interconnect_controller.vcd");
    $dumpvars(0,tb_interconnect_controller);

end

endmodule

RISCV_single/src/interconnect_controller.vcd
$date
	Tue Jul 07 02:18:52 2026
$end
$version
	Icarus Verilog
$end
$timescale
	1ps
$end
$scope module tb_interconnect_controller $end
$var wire 4 ! master_write_strb [3:0] $end
$var wire 1 " master_write_resp_ready $end
$var wire 1 # master_write_data_valid $end
$var wire 32 $ master_write_data [31:0] $end
$var wire 1 % master_write_addr_valid $end
$var wire 32 & master_write_addr [31:0] $end
$var wire 1 ' master_read_data_ready $end
$var wire 1 ( master_read_addr_valid $end
$var wire 32 ) master_read_addr [31:0] $end
$var wire 1 * cache_write_done $end
$var wire 1 + cache_read_done $end
$var wire 32 , cache_read_data [31:0] $end
$var wire 1 - cache_busy $end
$var reg 32 . cache_address [31:0] $end
$var reg 1 / cache_read_req $end
$var reg 32 0 cache_write_data [31:0] $end
$var reg 1 1 cache_write_req $end
$var reg 4 2 cache_write_strb [3:0] $end
$var reg 1 3 clk $end
$var reg 1 4 master_read_addr_ready $end
$var reg 32 5 master_read_data [31:0] $end
$var reg 1 6 master_read_data_valid $end
$var reg 2 7 master_read_resp [1:0] $end
$var reg 1 8 master_write_addr_ready $end
$var reg 1 9 master_write_data_ready $end
$var reg 2 : master_write_resp [1:0] $end
$var reg 1 ; master_write_resp_valid $end
$var reg 1 < rst $end
$scope module dut $end
$var wire 32 = cache_address [31:0] $end
$var wire 1 / cache_read_req $end
$var wire 32 > cache_write_data [31:0] $end
$var wire 1 1 cache_write_req $end
$var wire 4 ? cache_write_strb [3:0] $end
$var wire 1 3 clk $end
$var wire 1 4 master_read_addr_ready $end
$var wire 32 @ master_read_data [31:0] $end
$var wire 1 6 master_read_data_valid $end
$var wire 2 A master_read_resp [1:0] $end
$var wire 1 8 master_write_addr_ready $end
$var wire 1 9 master_write_data_ready $end
$var wire 2 B master_write_resp [1:0] $end
$var wire 1 ; master_write_resp_valid $end
$var wire 1 < rst $end
$var parameter 3 C IDLE $end
$var parameter 3 D READ_ADDR $end
$var parameter 3 E READ_DATA $end
$var parameter 3 F WRITE $end
$var parameter 3 G WRITE_RESP $end
$var reg 1 - cache_busy $end
$var reg 32 H cache_read_data [31:0] $end
$var reg 1 + cache_read_done $end
$var reg 1 * cache_write_done $end
$var reg 32 I master_read_addr [31:0] $end
$var reg 1 ( master_read_addr_valid $end
$var reg 1 ' master_read_data_ready $end
$var reg 32 J master_write_addr [31:0] $end
$var reg 1 % master_write_addr_valid $end
$var reg 32 K master_write_data [31:0] $end
$var reg 1 # master_write_data_valid $end
$var reg 1 " master_write_resp_ready $end
$var reg 4 L master_write_strb [3:0] $end
$var reg 3 M next_state [2:0] $end
$var reg 32 N req_address [31:0] $end
$var reg 32 O req_write_data [31:0] $end
$var reg 4 P req_write_strb [3:0] $end
$var reg 3 Q state [2:0] $end
$upscope $end
$upscope $end
$enddefinitions $end
$comment Show the parameter values. $end
$dumpall
b100 G
b11 F
b10 E
b1 D
b0 C
$end
#0
$dumpvars
b0 Q
b0 P
b0 O
b0 N
b0 M
b0 L
b0 K
b0 J
b0 I
b0 H
b0 B
b0 A
b0 @
b0 ?
b0 >
b0 =
1<
0;
b0 :
09
08
b0 7
06
b0 5
04
03
b0 2
01
b0 0
0/
b0 .
0-
b0 ,
0+
0*
b0 )
0(
0'
b0 &
0%
b0 $
0#
0"
b0 !
$end
#5000
13
#10000
03
#15000
13
#20000
b1 M
03
1/
b100000000 .
b100000000 =
0<
#25000
1(
b100000000 )
b100000000 I
1-
b100000000 N
b1 Q
13
#30000
1(
b100000000 )
b100000000 I
03
0/
#35000
13
#40000
b10 M
1(
b100000000 )
b100000000 I
03
14
#45000
1'
0(
b0 )
b0 I
b10 Q
13
#50000
1'
03
04
#55000
13
#60000
03
#65000
13
#70000
b0 M
b10010001101000101011001111000 ,
b10010001101000101011001111000 H
1+
1'
03
16
b10010001101000101011001111000 5
b10010001101000101011001111000 @
#75000
0'
b0 ,
b0 H
0+
0-
b0 Q
13
#80000
03
06
#85000
13
#90000
03
#95000
13
#100000
b11 M
03
11
b1111 2
b1111 ?
b11011110101011011011111011101111 0
b11011110101011011011111011101111 >
b1000000000 .
b1000000000 =
#105000
1#
b1111 !
b1111 L
b11011110101011011011111011101111 $
b11011110101011011011111011101111 K
1%
b1000000000 &
b1000000000 J
1-
b1111 P
b11011110101011011011111011101111 O
b1000000000 N
b11 Q
13
#110000
1#
b1111 !
b1111 L
b11011110101011011011111011101111 $
b11011110101011011011111011101111 K
1%
b1000000000 &
b1000000000 J
03
01
#115000
13
#120000
b100 M
1#
b1111 !
b1111 L
b11011110101011011011111011101111 $
b11011110101011011011111011101111 K
1%
b1000000000 &
b1000000000 J
03
19
18
#125000
1"
0#
b0 !
b0 L
b0 $
b0 K
0%
b0 &
b0 J
b100 Q
13
#130000
1"
03
09
08
#135000
13
#140000
03
#145000
13
#150000
b0 M
1*
1"
03
1;
#155000
0"
0*
0-
b0 Q
13
#160000
03
0;
